PlistParser/Base64.py
PlistParser/Extend.py
PlistParser/Info.py
PlistParser/Plist.py
PlistParser/PlistParser.py
PlistParser/__init__.py
PlistParser-2023.7.28.0.dist-info/LICENSE.txt
PlistParser-2023.7.28.0.dist-info/METADATA
PlistParser-2023.7.28.0.dist-info/WHEEL
PlistParser-2023.7.28.0.dist-info/top_level.txt
PlistParser-2023.7.28.0.dist-info/RECORD
