Metadata-Version: 2.1
Name: PlistParser
Version: 2023.7.28.0
Summary: Extension package for .plist file parsing
Home-page: https://github.com/whiteEelsYikes/PlistParser
Author: white-EelsYikes
Author-email: 2172989337@qq.com
Keywords: Plist,PlistParser
Platform: Windows
Platform: Linux
Platform: MacOS
Classifier: Development Status :: 4 - Beta
Classifier: Intended Audience :: Developers
Classifier: Topic :: Software Development :: Build Tools
Classifier: Programming Language :: Python :: 3
Classifier: License :: OSI Approved :: MIT License
Classifier: Operating System :: OS Independent
Requires-Python: >=3.6
License-File: LICENSE.txt
